{"language":"en","textAngle":0.0,"orientation":"Up","regions":[{"boundingBox":"198,33,849,666","lines":[{"boundingBox":"198,33,170,32","words":[{"boundingBox":"198,33,170,32","text":"Deviance"}]},{"boundingBox":"233,128,779,32","words":[{"boundingBox":"233,128,214,26","text":"Generalization"},{"boundingBox":"459,128,29,26","text":"of"},{"boundingBox":"498,136,60,18","text":"sum"},{"boundingBox":"569,128,30,26","text":"of"},{"boundingBox":"609,128,117,32","text":"squared"},{"boundingBox":"739,128,129,26","text":"residuals"},{"boundingBox":"880,128,85,26","text":"based"},{"boundingBox":"977,136,35,18","text":"on"}]},{"boundingBox":"234,170,229,26","words":[{"boundingBox":"234,170,141,26","text":"likelihood"},{"boundingBox":"388,170,75,26","text":"ratio:"}]},{"boundingBox":"467,209,347,41","words":[{"boundingBox":"467,217,21,24","text":"D"},{"boundingBox":"500,225,16,9","text":"="},{"boundingBox":"528,209,74,41","text":"Edi"},{"boundingBox":"616,224,16,10","text":"="},{"boundingBox":"647,217,42,24","text":"-2"},{"boundingBox":"699,215,115,33","text":"logL+c"}]},{"boundingBox":"232,268,815,26","words":[{"boundingBox":"232,268,94,26","text":"where"},{"boundingBox":"336,270,13,24","text":"L"},{"boundingBox":"359,268,21,26","text":"is"},{"boundingBox":"389,268,49,26","text":"the"},{"boundingBox":"449,268,141,26","text":"likelihood"},{"boundingBox":"602,268,29,26","text":"of"},{"boundingBox":"639,268,49,26","text":"the"},{"boundingBox":"699,268,91,26","text":"model"},{"boundingBox":"801,268,53,26","text":"and"},{"boundingBox":"865,275,15,19","text":"c"},{"boundingBox":"889,268,20,26","text":"is"},{"boundingBox":"919,270,128,24","text":"constant"}]},{"boundingBox":"232,310,550,32","words":[{"boundingBox":"232,310,61,26","text":"that"},{"boundingBox":"303,310,126,32","text":"depends"},{"boundingBox":"440,318,36,18","text":"on"},{"boundingBox":"487,310,63,26","text":"data"},{"boundingBox":"563,310,49,26","text":"but"},{"boundingBox":"623,312,48,24","text":"not"},{"boundingBox":"682,310,100,26","text":"model."}]},{"boundingBox":"270,360,718,32","words":[{"boundingBox":"270,368,18,17","text":"•"},{"boundingBox":"309,360,151,26","text":"Difference"},{"boundingBox":"471,360,128,26","text":"between"},{"boundingBox":"611,360,145,26","text":"deviances"},{"boundingBox":"767,360,156,32","text":"equivalent"},{"boundingBox":"932,362,30,24","text":"to"},{"boundingBox":"973,368,15,18","text":"a"}]},{"boundingBox":"309,402,293,26","words":[{"boundingBox":"309,402,141,26","text":"likelihood"},{"boundingBox":"463,402,66,26","text":"ratio"},{"boundingBox":"539,404,63,24","text":"test."}]},{"boundingBox":"308,440,638,38","words":[{"boundingBox":"308,446,33,30","text":"DI"},{"boundingBox":"355,459,23,3","text":"—"},{"boundingBox":"390,446,34,30","text":"D2"},{"boundingBox":"476,440,34,38","text":"X2"},{"boundingBox":"575,444,94,26","text":"where"},{"boundingBox":"679,452,25,24","text":"q"},{"boundingBox":"714,444,21,26","text":"is"},{"boundingBox":"746,444,29,26","text":"df"},{"boundingBox":"784,444,41,26","text":"for"},{"boundingBox":"837,444,90,26","text":"model"},{"boundingBox":"939,444,7,26","text":"i"}]},{"boundingBox":"308,487,139,32","words":[{"boundingBox":"308,487,139,32","text":"assuming"}]},{"boundingBox":"322,533,40,34","words":[{"boundingBox":"322,533,40,34","text":"a"}]},{"boundingBox":"382,538,306,23","words":[{"boundingBox":"382,538,93,23","text":"smaller"},{"boundingBox":"484,538,78,23","text":"model"},{"boundingBox":"572,539,17,22","text":"is"},{"boundingBox":"598,540,90,21","text":"correct"}]},{"boundingBox":"383,580,233,23","words":[{"boundingBox":"383,580,91,23","text":"models"},{"boundingBox":"483,587,40,16","text":"are"},{"boundingBox":"533,580,83,23","text":"nested"}]},{"boundingBox":"382,622,400,28","words":[{"boundingBox":"382,622,168,23","text":"distributional"},{"boundingBox":"561,623,159,27","text":"assumptions"},{"boundingBox":"729,624,53,21","text":"true"}]},{"boundingBox":"309,667,730,32","words":[{"boundingBox":"309,667,55,26","text":"Null"},{"boundingBox":"376,667,132,26","text":"deviance"},{"boundingBox":"518,667,21,26","text":"is"},{"boundingBox":"548,667,42,26","text":"for"},{"boundingBox":"602,667,90,26","text":"model"},{"boundingBox":"703,667,64,26","text":"with"},{"boundingBox":"779,667,62,32","text":"only"},{"boundingBox":"851,674,34,19","text":"an"},{"boundingBox":"897,667,142,32","text":"intercept."}]}]},{"boundingBox":"1077,674,20,14","lines":[{"boundingBox":"1077,674,20,14","words":[{"boundingBox":"1077,674,20,14","text":"14"}]}]}]}