{"language":"en","textAngle":0.0,"orientation":"Up","regions":[{"boundingBox":"179,196,20,15","lines":[{"boundingBox":"179,196,20,15","words":[{"boundingBox":"179,196,20,15","text":"ed"}]}]},{"boundingBox":"219,123,341,115","lines":[{"boundingBox":"239,123,312,48","words":[{"boundingBox":"239,123,312,48","text":"bit.ly/etc3580"}]},{"boundingBox":"219,199,130,10","words":[{"boundingBox":"219,199,52,10","text":"ETC3580"},{"boundingBox":"275,204,6,2","text":"-"},{"boundingBox":"285,199,64,10","text":"Discussion"}]},{"boundingBox":"529,230,31,8","words":[{"boundingBox":"529,230,31,8","text":"Cancel"}]}]},{"boundingBox":"952,196,14,14","lines":[{"boundingBox":"952,196,14,14","words":[{"boundingBox":"952,196,14,14","text":".11"}]}]},{"boundingBox":"787,230,82,10","lines":[{"boundingBox":"787,230,82,10","words":[{"boundingBox":"787,230,25,9","text":"New"},{"boundingBox":"816,230,53,10","text":"Question"}]}]},{"boundingBox":"1095,230,21,8","lines":[{"boundingBox":"1095,230,21,8","words":[{"boundingBox":"1095,230,21,8","text":"Post"}]}]},{"boundingBox":"690,290,44,10","lines":[{"boundingBox":"690,290,44,10","words":[{"boundingBox":"690,290,44,10","text":"Question"}]}]},{"boundingBox":"999,688,21,8","lines":[{"boundingBox":"999,688,21,8","words":[{"boundingBox":"999,688,21,8","text":"Post"}]}]}]}