{"language":"en","textAngle":0.0,"orientation":"Up","regions":[{"boundingBox":"199,34,466,537","lines":[{"boundingBox":"199,34,265,33","words":[{"boundingBox":"199,34,115,33","text":"Linear"},{"boundingBox":"327,34,137,33","text":"Models"}]},{"boundingBox":"309,211,138,28","words":[{"boundingBox":"309,211,138,28","text":"Response:"}]},{"boundingBox":"273,248,229,31","words":[{"boundingBox":"273,256,16,16","text":"•"},{"boundingBox":"309,248,146,25","text":"Predictors:"},{"boundingBox":"466,256,36,23","text":"Xl,"}]},{"boundingBox":"309,289,75,23","words":[{"boundingBox":"309,289,75,23","text":"Error:"}]},{"boundingBox":"235,333,232,31","words":[{"boundingBox":"235,335,41,23","text":"Let"},{"boundingBox":"285,341,16,23","text":"y"},{"boundingBox":"311,343,15,8","text":"="},{"boundingBox":"339,333,44,31","text":"(Yl,"},{"boundingBox":"453,341,14,23","text":"Y"}]},{"boundingBox":"589,545,76,26","words":[{"boundingBox":"589,545,76,26","text":"Xp—l,n"}]}]},{"boundingBox":"233,373,109,253","lines":[{"boundingBox":"234,373,50,25","words":[{"boundingBox":"234,373,50,25","text":"and"}]},{"boundingBox":"329,408,13,22","words":[{"boundingBox":"329,408,13,22","text":"1"}]},{"boundingBox":"329,447,13,23","words":[{"boundingBox":"329,447,13,23","text":"1"}]},{"boundingBox":"329,539,13,23","words":[{"boundingBox":"329,539,13,23","text":"1"}]},{"boundingBox":"233,602,68,24","words":[{"boundingBox":"233,602,68,24","text":"Then"}]}]},{"boundingBox":"589,413,27,27","lines":[{"boundingBox":"589,413,27,27","words":[{"boundingBox":"589,413,27,27","text":"XP"}]}]},{"boundingBox":"762,149,265,352","lines":[{"boundingBox":"762,149,72,27","words":[{"boundingBox":"762,149,72,27","text":"p—IXp"}]},{"boundingBox":"783,333,75,31","words":[{"boundingBox":"783,343,14,8","text":"="},{"boundingBox":"810,333,48,31","text":"(00,"}]},{"boundingBox":"763,471,264,30","words":[{"boundingBox":"763,472,53,29","text":"(the"},{"boundingBox":"827,472,84,25","text":"model"},{"boundingBox":"923,471,104,30","text":"matrix)."}]}]},{"boundingBox":"369,545,46,22","lines":[{"boundingBox":"369,545,46,22","words":[{"boundingBox":"369,545,46,22","text":"Xin"}]}]},{"boundingBox":"1079,675,18,14","lines":[{"boundingBox":"1079,675,18,14","words":[{"boundingBox":"1079,675,18,14","text":"11"}]}]}]}