{"language":"en","textAngle":0.0,"orientation":"Up","regions":[{"boundingBox":"200,34,898,655","lines":[{"boundingBox":"200,34,392,40","words":[{"boundingBox":"200,36,23,30","text":"R"},{"boundingBox":"235,34,186,40","text":"modelling"},{"boundingBox":"434,34,158,33","text":"notation"}]},{"boundingBox":"235,298,349,36","words":[{"boundingBox":"235,301,54,25","text":"fit"},{"boundingBox":"314,304,34,19","text":"<—"},{"boundingBox":"361,301,48,24","text":"nm"},{"boundingBox":"417,298,167,36","text":"(response"}]},{"boundingBox":"274,350,227,30","words":[{"boundingBox":"274,350,227,30","text":"data=tibble)"}]},{"boundingBox":"501,480,447,35","words":[{"boundingBox":"501,490,16,10","text":"="},{"boundingBox":"574,486,18,18","text":"+"},{"boundingBox":"601,480,72,35","text":"\"IXI"},{"boundingBox":"684,485,18,19","text":"+"},{"boundingBox":"712,480,72,34","text":"{3212"},{"boundingBox":"794,485,18,19","text":"+"},{"boundingBox":"822,480,73,35","text":"/33X3"},{"boundingBox":"905,485,18,19","text":"+"},{"boundingBox":"932,489,16,19","text":"E"}]},{"boundingBox":"334,490,153,26","words":[{"boundingBox":"334,490,153,26","text":"response"}]},{"boundingBox":"1079,675,19,14","words":[{"boundingBox":"1079,675,19,14","text":"14"}]}]}]}